orbit_component_buttonlegal/__init__.py
orbit_component_buttonlegal/__main__.py
orbit_component_buttonlegal/plugin.py
orbit_component_buttonlegal/schema/MyTable.py
orbit_component_buttonlegal/version.py
orbit_component_buttonlegal-1.0.21.dist-info/METADATA
orbit_component_buttonlegal-1.0.21.dist-info/WHEEL
orbit_component_buttonlegal-1.0.21.dist-info/RECORD
